moman/__init__.py
moman/interface/__init__.py
moman/interface/__pycache__/__init__.cpython-313.pyc
moman/interface/__pycache__/handle.cpython-313.pyc
moman/manager/__init__.py
moman/manager/__pycache__/__init__.cpython-313.pyc
moman/manager/__pycache__/wrapper.cpython-313.pyc
moman/manager/wrapper.py
moman-bin/cli/__init__.py
moman-bin/cli/__pycache__/__init__.cpython-313.pyc
moman-bin/constants.py
moman-bin/errors.py
moman-bin/handler/__init__.py
moman-bin/handler/__pycache__/__init__.cpython-313.pyc
moman-bin/handler/__pycache__/base.cpython-313.pyc
moman-bin/handler/__pycache__/import_utils.cpython-313.pyc
moman-bin/handler/__pycache__/modular.cpython-313.pyc
moman-bin/handler/add/__init__.py
moman-bin/handler/add/__pycache__/__init__.cpython-313.pyc
moman-bin/handler/add/__pycache__/handler.cpython-313.pyc
moman-bin/handler/add/handler.py
moman-bin/handler/base.py
moman-bin/handler/build/__init__.py
moman-bin/handler/build/__pycache__/__init__.cpython-313.pyc
moman-bin/handler/build/__pycache__/handler.cpython-313.pyc
moman-bin/handler/build/__pycache__/manger.cpython-313.pyc
moman-bin/handler/build/handler.py
moman-bin/handler/build/manger.py
moman-bin/handler/create/__init__.py
moman-bin/handler/create/__pycache__/__init__.cpython-312.pyc
moman-bin/handler/create/__pycache__/__init__.cpython-313.pyc
moman-bin/handler/create/__pycache__/handler.cpython-312.pyc
moman-bin/handler/create/__pycache__/handler.cpython-313.pyc
moman-bin/handler/create/__pycache__/template.cpython-313.pyc
moman-bin/handler/create/handler.py
moman-bin/handler/create/template.py
moman-bin/handler/import_utils.py
moman-bin/handler/modular.py
moman-bin/handler/new/__init__.py
moman-bin/handler/new/__pycache__/__init__.cpython-313.pyc
moman-bin/handler/new/__pycache__/handler.cpython-313.pyc
moman-bin/handler/new/__pycache__/template.cpython-313.pyc
moman-bin/handler/new/handler.py
moman-bin/handler/new/template.py
moman-bin/info/__init__.py
moman-0.0.1.dist-info/METADATA
moman-0.0.1.dist-info/WHEEL
moman-0.0.1.dist-info/RECORD
