Metadata-Version: 2.3
Name: moman
Version: 0.0.1
Summary: 
Author: fucloud-macbook
Author-email: 270928474@qq.com
Requires-Python: >=3.12
Classifier: Programming Language :: Python :: 3
Classifier: Programming Language :: Python :: 3.12
Classifier: Programming Language :: Python :: 3.13
Requires-Dist: pyyaml (>=6.0.2,<7.0.0)
